CHANGELOG.txt
LICENSE.txt
MANIFEST.in
README.rst
pyproject.toml
setup.py
fdint/__init__.pxd
fdint/__init__.py
fdint/_fdint.c
fdint/_fdint.pxd
fdint/_fdint.pyx
fdint/dfd.c
fdint/dfd.pyx
fdint/dgfd.c
fdint/dgfd.pyx
fdint/fd.c
fdint/fd.pyx
fdint/gfd.c
fdint/gfd.pyx
fdint/ifd.c
fdint/ifd.pyx
fdint/scfd.c
fdint/scfd.pxd
fdint/scfd.pyx
fdint/version.py
fdint/examples/__init__.py
fdint/examples/plot.py
fdint/tests/__init__.py
fdint/tests/__main__.py
fdint/tests/test_fd.py
fdint/tests/test_gfd.py
fdint/tests/test_ifd.py
fdint/tests/test_scfd.py
fdint_py3.egg-info/PKG-INFO
fdint_py3.egg-info/SOURCES.txt
fdint_py3.egg-info/dependency_links.txt
fdint_py3.egg-info/requires.txt
fdint_py3.egg-info/top_level.txt