Metadata-Version: 2.1
Name: fdint-py3
Version: 2.0.2
Summary: A free, open-source python package for quickly and precisely approximating Fermi-Dirac integrals.
Home-page: http://scott-maddox.github.io/fdint
Author: Scott J. Maddox
Author-email: smaddox@utexas.edu
License: BSD
License-File: LICENSE.txt
